x23340355_aws_service_pkg/__init__.py
x23340355_aws_service_pkg/aws_service.py
x23340355_aws_service_pkg-0.0.2.dist-info/LICENSE
x23340355_aws_service_pkg-0.0.2.dist-info/METADATA
x23340355_aws_service_pkg-0.0.2.dist-info/WHEEL
x23340355_aws_service_pkg-0.0.2.dist-info/top_level.txt
x23340355_aws_service_pkg-0.0.2.dist-info/RECORD
